setup.py
sqlpython/__init__.py
sqlpython/completion.py
sqlpython/connections.py
sqlpython/dbapiext.py
sqlpython/defaultdict.py
sqlpython/imagedetect.py
sqlpython/metadata.py
sqlpython/mysqlpy.py
sqlpython/output_templates.py
sqlpython/plothandler.py
sqlpython/sqlpyPlus.py
sqlpython/sqlpython.py
sqlpython.egg-info/PKG-INFO
sqlpython.egg-info/SOURCES.txt
sqlpython.egg-info/dependency_links.txt
sqlpython.egg-info/entry_points.txt
sqlpython.egg-info/requires.txt
sqlpython.egg-info/top_level.txt