Metadata-Version: 1.0
Name: sqlpython
Version: 1.7.3
Summary: Command-line interface to Oracle
Home-page: http://packages.python.org/sqlpython
Author: Luca Canali
Author-email: luca.canali@cern.ch
License: MIT
Keywords: client oracle database
Platform: any
